pyconnectify
