Metadata-Version: 2.1
Name: pyconnectify
Version: 0.0.3.1
Summary: Telecommunication and file management application
Home-page: https://gitlab.com/israelcunha/PyConnectify
Author: Israel Cunha
Author-email: ms.israel.cunha@gmail.com
License: MIT License
Keywords: ssh utp tcp tar redes network
Platform: UNKNOWN
Classifier: Programming Language :: Python :: 3
Classifier: Programming Language :: Python :: 3.6
Classifier: Programming Language :: Python :: 3.7
Classifier: License :: OSI Approved :: MIT License
Classifier: Operating System :: OS Independent
Requires-Python: >=3.6
